{"cameraMode":{"drawMode":0,"name":"Shaded","section":"Shading Mode"},"sceneLighting":false,"audioPlay":false,"sceneViewState":{"m_AlwaysRefresh":false,"showFog":true,"showSkybox":false,"showFlares":true,"showImageEffects":true,"showParticleSystems":true,"showVisualEffectGraphs":true,"m_FxEnabled":true},"in2DMode":false,"pivot":{"x":8.085953712463379,"y":1.080838918685913,"z":6.949744701385498},"rotation":{"x":-0.24702602624893189,"y":-0.054243676364421847,"z":0.013834542594850064,"w":-0.9674325585365295},"size":0.962994396686554,"orthographic":false}